Group1402122/__init__.py
Group1402122/module1.py
group1402122-0.2.8.dist-info/LICENSE
group1402122-0.2.8.dist-info/METADATA
group1402122-0.2.8.dist-info/WHEEL
group1402122-0.2.8.dist-info/top_level.txt
group1402122-0.2.8.dist-info/RECORD
