Metadata-Version: 2.2
Name: Group1402122
Version: 0.2.8
Summary: A test package for learning!
Author-email: Anton <s235256@dtu.dk>
License: MIT
License-File: LICENSE
Requires-Dist: numpy<3.0,>=2.0.2
Requires-Dist: pandas<3.0,>=2.2.3
Requires-Dist: anndata<1.0,>=0.11
Requires-Dist: scanpy<2.0,>=1.9.8
